LICENSE
README.md
setup.py
lion_tf/__init__.py
lion_tf/lion_tf.py
lion_tf.egg-info/PKG-INFO
lion_tf.egg-info/SOURCES.txt
lion_tf.egg-info/dependency_links.txt
lion_tf.egg-info/requires.txt
lion_tf.egg-info/top_level.txt